bioconverters/__init__.py
bioconverters/main.py
bioconverters/pmcxml.py
bioconverters/pubmedxml.py
bioconverters/utils.py
bioconverters-1.0.1.dist-info/LICENSE
bioconverters-1.0.1.dist-info/METADATA
bioconverters-1.0.1.dist-info/WHEEL
bioconverters-1.0.1.dist-info/top_level.txt
bioconverters-1.0.1.dist-info/RECORD
