Metadata-Version: 2.1
Name: bioconverters
Version: 1.0.1
Summary: Convert between NCBI pubmed/PMC and BIOC formats
Home-page: UNKNOWN
Author: Jake Lever
Author-email: jlever@stanford.edu
Maintainer: Jake Lever
Maintainer-email: jlever@stanford.edu
License: UNKNOWN
Platform: UNKNOWN
Requires-Python: >=3.6
License-File: LICENSE
Requires-Dist: bioc (<2,>=1.3)
Requires-Dist: typing-extensions
Provides-Extra: dev
Requires-Dist: black ; extra == 'dev'
Requires-Dist: flake8 ; extra == 'dev'
Requires-Dist: isort ; extra == 'dev'
Requires-Dist: mypy ; extra == 'dev'
Requires-Dist: biopython ; extra == 'dev'
Requires-Dist: snakemake ; extra == 'dev'
Requires-Dist: ftputil ; extra == 'dev'
Requires-Dist: requests ; extra == 'dev'
Requires-Dist: pytest ; extra == 'dev'
Requires-Dist: pytest-cov ; extra == 'dev'
Requires-Dist: hypothesis ; extra == 'dev'
Provides-Extra: test
Requires-Dist: biopython ; extra == 'test'
Requires-Dist: snakemake ; extra == 'test'
Requires-Dist: ftputil ; extra == 'test'
Requires-Dist: requests ; extra == 'test'
Requires-Dist: pytest ; extra == 'test'
Requires-Dist: pytest-cov ; extra == 'test'
Requires-Dist: hypothesis ; extra == 'test'
